[{"relativeZVelocity":0,"relativeZAcceleration":0},{"relativeZVelocity":0.00017441437,"relativeZAcceleration":0.00017441437},{"relativeZVelocity":0.0010456368,"relativeZAcceleration":0.00087122247},{"relativeZVelocity":-0.00019898266,"relativeZAcceleration":-0.0012446195},{"relativeZVelocity":-0.0024689995,"relativeZAcceleration":-0.0022700168},{"relativeZVelocity":0.0041300394,"relativeZAcceleration":0.006599039},{"relativeZVelocity":0.005183775,"relativeZAcceleration":0.0010537356},{"relativeZVelocity":0.0039206464,"relativeZAcceleration":-0.0012631286},{"relativeZVelocity":-0.0034055132,"relativeZAcceleration":-0.0073261596},{"relativeZVelocity":-0.006019525,"relativeZAcceleration":-0.002614012},{"relativeZVelocity":-0.0041081086,"relativeZAcceleration":0.0019114166},{"relativeZVelocity":0.0014318526,"relativeZAcceleration":0.005539961},{"relativeZVelocity":0.00022113696,"relativeZAcceleration":-0.0012107156},{"relativeZVelocity":0.0005617663,"relativeZAcceleration":0.00034062937},{"relativeZVelocity":-0.00090458617,"relativeZAcceleration":-0.0014663525}]