[{"accelerationMagnitude":0,"velocityMagnitude":0,"extensionRatio":10.499705,"handCompactness":0.19843574},{"accelerationMagnitude":0.0056188973,"velocityMagnitude":0.0056188973,"extensionRatio":9.604243,"handCompactness":0.1975282},{"accelerationMagnitude":-0.00081500644,"velocityMagnitude":0.004803891,"extensionRatio":17.139336,"handCompactness":0.20132971},{"accelerationMagnitude":0.0037366818,"velocityMagnitude":0.008540573,"extensionRatio":24.78264,"handCompactness":0.20355889},{"accelerationMagnitude":0.002029187,"velocityMagnitude":0.01056976,"extensionRatio":24.429722,"handCompactness":0.20660476},{"accelerationMagnitude":-0.0023104139,"velocityMagnitude":0.008259346,"extensionRatio":19.59754,"handCompactness":0.20642193},{"accelerationMagnitude":0.0065389425,"velocityMagnitude":0.014798288,"extensionRatio":20.545248,"handCompactness":0.20567146},{"accelerationMagnitude":-0.0009410009,"velocityMagnitude":0.013857287,"extensionRatio":14.37643,"handCompactness":0.20354196},{"accelerationMagnitude":-0.003265337,"velocityMagnitude":0.01059195,"extensionRatio":13.367827,"handCompactness":0.20213945},{"accelerationMagnitude":0.015348941,"velocityMagnitude":0.025940891,"extensionRatio":5.783076,"handCompactness":0.1968908},{"accelerationMagnitude":-0.008545699,"velocityMagnitude":0.017395193,"extensionRatio":4.1900897,"handCompactness":0.19486602},{"accelerationMagnitude":-0.008838937,"velocityMagnitude":0.008556256,"extensionRatio":4.360285,"handCompactness":0.19213834},{"accelerationMagnitude":-0.008094823,"velocityMagnitude":0.00046143337,"extensionRatio":3.7972343,"handCompactness":0.1898956},{"accelerationMagnitude":0.0019948708,"velocityMagnitude":0.0024563042,"extensionRatio":3.8004553,"handCompactness":0.18909046},{"accelerationMagnitude":0.0062612803,"velocityMagnitude":0.008717584,"extensionRatio":3.697876,"handCompactness":0.18837172},{"accelerationMagnitude":0.008227135,"velocityMagnitude":0.01694472,"extensionRatio":4.168219,"handCompactness":0.1881263},{"accelerationMagnitude":-0.0096673565,"velocityMagnitude":0.007277363,"extensionRatio":5.0791035,"handCompactness":0.1920863},{"accelerationMagnitude":0.0015783645,"velocityMagnitude":0.0088557275,"extensionRatio":6.824264,"handCompactness":0.19514927},{"accelerationMagnitude":-0.0038902117,"velocityMagnitude":0.004965516,"extensionRatio":8.01,"handCompactness":0.19749686},{"accelerationMagnitude":-0.0014842278,"velocityMagnitude":0.003481288,"extensionRatio":10.1717,"handCompactness":0.20116082},{"accelerationMagnitude":0.0021577133,"velocityMagnitude":0.0056390013,"extensionRatio":9.9168415,"handCompactness":0.20105545},{"accelerationMagnitude":-0.0028494587,"velocityMagnitude":0.0027895425,"extensionRatio":11.65588,"handCompactness":0.20323738},{"accelerationMagnitude":0.00010333466,"velocityMagnitude":0.0028928772,"extensionRatio":11.658447,"handCompactness":0.2036191},{"accelerationMagnitude":0.00029117404,"velocityMagnitude":0.0031840513,"extensionRatio":10.465052,"handCompactness":0.20204684},{"accelerationMagnitude":-0.0004601141,"velocityMagnitude":0.0027239372,"extensionRatio":12.414054,"handCompactness":0.20309171},{"accelerationMagnitude":0.00038110442,"velocityMagnitude":0.0031050416,"extensionRatio":11.615599,"handCompactness":0.20278387},{"accelerationMagnitude":0.0008599912,"velocityMagnitude":0.0039650328,"extensionRatio":10.957372,"handCompactness":0.2009285},{"accelerationMagnitude":-0.00033534854,"velocityMagnitude":0.0036296842,"extensionRatio":11.863385,"handCompactness":0.20254096},{"accelerationMagnitude":0.0011587881,"velocityMagnitude":0.0047884723,"extensionRatio":11.325155,"handCompactness":0.20096883},{"accelerationMagnitude":-0.0006513484,"velocityMagnitude":0.004137124,"extensionRatio":12.471908,"handCompactness":0.20144066}]