[{"relativeYAcceleration":0,"relativeYVelocity":0,"palmStabilityScore":0},{"relativeYAcceleration":-0.00056809187,"relativeYVelocity":-0.00056809187,"palmStabilityScore":0.0005736649},{"relativeYAcceleration":0.001019448,"relativeYVelocity":0.00045135617,"palmStabilityScore":0.0014670491},{"relativeYAcceleration":-0.0011031926,"relativeYVelocity":-0.0006518364,"palmStabilityScore":0.005479008},{"relativeYAcceleration":-0.004717022,"relativeYVelocity":-0.0053688586,"palmStabilityScore":0.0083937645},{"relativeYAcceleration":-0.0018341243,"relativeYVelocity":-0.007202983,"palmStabilityScore":0.0035322905},{"relativeYAcceleration":0.007787168,"relativeYVelocity":0.0005841851,"palmStabilityScore":0.00806424},{"relativeYAcceleration":-0.0013116598,"relativeYVelocity":-0.0007274747,"palmStabilityScore":0.0034449399},{"relativeYAcceleration":0.0014354289,"relativeYVelocity":0.00070795417,"palmStabilityScore":0.005465716},{"relativeYAcceleration":0.009261906,"relativeYVelocity":0.00996986,"palmStabilityScore":0.008692682},{"relativeYAcceleration":-0.004146427,"relativeYVelocity":0.0058234334,"palmStabilityScore":0.013247877},{"relativeYAcceleration":-0.01047653,"relativeYVelocity":-0.004653096,"palmStabilityScore":0.013503194},{"relativeYAcceleration":-0.0153954625,"relativeYVelocity":-0.020048559,"palmStabilityScore":0.015920788},{"relativeYAcceleration":0.016041696,"relativeYVelocity":-0.0040068626,"palmStabilityScore":0.007840335},{"relativeYAcceleration":0.0034153461,"relativeYVelocity":-0.0005915165,"palmStabilityScore":0.003527552},{"relativeYAcceleration":0.011256546,"relativeYVelocity":0.010665029,"palmStabilityScore":0.0055370033},{"relativeYAcceleration":-0.0026207268,"relativeYVelocity":0.008044302,"palmStabilityScore":0.009530008},{"relativeYAcceleration":-0.0006158352,"relativeYVelocity":0.0074284673,"palmStabilityScore":0.0065844655},{"relativeYAcceleration":-0.0018854141,"relativeYVelocity":0.005543053,"palmStabilityScore":0.014672041},{"relativeYAcceleration":-0.0024827123,"relativeYVelocity":0.0030603409,"palmStabilityScore":0.0036314428},{"relativeYAcceleration":-0.0032995045,"relativeYVelocity":-0.00023916364,"palmStabilityScore":0.0034640133},{"relativeYAcceleration":0.0025312603,"relativeYVelocity":0.0022920966,"palmStabilityScore":0.0014427602},{"relativeYAcceleration":-0.0022467673,"relativeYVelocity":4.5329332e-05,"palmStabilityScore":0.004011184},{"relativeYAcceleration":0.00066155195,"relativeYVelocity":0.0007068813,"palmStabilityScore":0.0016409159},{"relativeYAcceleration":-0.00045374036,"relativeYVelocity":0.00025314093,"palmStabilityScore":0.0014170408}]