[{"handCompactness":0.19622235,"extensionRatio":4.8899407,"velocityMagnitude":0,"accelerationMagnitude":0},{"handCompactness":0.19602278,"extensionRatio":4.879325,"velocityMagnitude":0.0009522902,"accelerationMagnitude":0.0009522902},{"handCompactness":0.19632009,"extensionRatio":4.838256,"velocityMagnitude":0.0012956284,"accelerationMagnitude":0.00034333818},{"handCompactness":0.19620179,"extensionRatio":4.7739844,"velocityMagnitude":0.0010091971,"accelerationMagnitude":-0.00028643128},{"handCompactness":0.19614932,"extensionRatio":4.8248262,"velocityMagnitude":0.0005386697,"accelerationMagnitude":-0.0004705274},{"handCompactness":0.19612673,"extensionRatio":4.8341365,"velocityMagnitude":0.0010321655,"accelerationMagnitude":0.0004934958},{"handCompactness":0.19608885,"extensionRatio":4.863742,"velocityMagnitude":0.0009837467,"accelerationMagnitude":-4.8418762e-05},{"handCompactness":0.19603333,"extensionRatio":4.8410764,"velocityMagnitude":0.00046553614,"accelerationMagnitude":-0.0005182106},{"handCompactness":0.1956915,"extensionRatio":4.8919373,"velocityMagnitude":0.00074730004,"accelerationMagnitude":0.0002817639},{"handCompactness":0.19582765,"extensionRatio":4.8113146,"velocityMagnitude":0.00013017523,"accelerationMagnitude":-0.00061712484},{"handCompactness":0.19593102,"extensionRatio":4.862511,"velocityMagnitude":0.0006167787,"accelerationMagnitude":0.00048660344},{"handCompactness":0.19558886,"extensionRatio":4.8674436,"velocityMagnitude":0.00055716676,"accelerationMagnitude":-5.961192e-05},{"handCompactness":0.19601502,"extensionRatio":4.77893,"velocityMagnitude":0.0011593276,"accelerationMagnitude":0.0006021608},{"handCompactness":0.19599703,"extensionRatio":4.8494425,"velocityMagnitude":0.0007790864,"accelerationMagnitude":-0.0003802412},{"handCompactness":0.1957035,"extensionRatio":4.7845592,"velocityMagnitude":0.0005425942,"accelerationMagnitude":-0.0002364922},{"handCompactness":0.19649144,"extensionRatio":4.7660384,"velocityMagnitude":0.00033743784,"accelerationMagnitude":-0.00020515634},{"handCompactness":0.19624835,"extensionRatio":4.7072678,"velocityMagnitude":0.0006335073,"accelerationMagnitude":0.00029606948},{"handCompactness":0.19663823,"extensionRatio":4.767424,"velocityMagnitude":0.000764938,"accelerationMagnitude":0.00013143069},{"handCompactness":0.19661434,"extensionRatio":4.781773,"velocityMagnitude":0.00032464913,"accelerationMagnitude":-0.0004402889},{"handCompactness":0.19649166,"extensionRatio":4.855257,"velocityMagnitude":0.0009868876,"accelerationMagnitude":0.00066223845},{"handCompactness":0.19657537,"extensionRatio":4.795574,"velocityMagnitude":0.0009280098,"accelerationMagnitude":-5.8877806e-05},{"handCompactness":0.1966089,"extensionRatio":4.753518,"velocityMagnitude":0.0006366582,"accelerationMagnitude":-0.00029135158},{"handCompactness":0.19626117,"extensionRatio":4.774777,"velocityMagnitude":0.00063286274,"accelerationMagnitude":-3.7954887e-06},{"handCompactness":0.19622758,"extensionRatio":4.7907343,"velocityMagnitude":0.0009121617,"accelerationMagnitude":0.00027929898},{"handCompactness":0.19600901,"extensionRatio":4.776072,"velocityMagnitude":0.0011331158,"accelerationMagnitude":0.00022095413},{"handCompactness":0.19590628,"extensionRatio":4.738775,"velocityMagnitude":0.0007346816,"accelerationMagnitude":-0.00039843423},{"handCompactness":0.19652514,"extensionRatio":4.767062,"velocityMagnitude":0.00048322752,"accelerationMagnitude":-0.0002514541},{"handCompactness":0.19629288,"extensionRatio":4.7795634,"velocityMagnitude":0.00048494307,"accelerationMagnitude":1.7155544e-06},{"handCompactness":0.19613606,"extensionRatio":4.853958,"velocityMagnitude":0.00047123028,"accelerationMagnitude":-1.3712794e-05},{"handCompactness":0.19613867,"extensionRatio":4.822488,"velocityMagnitude":0.00052773353,"accelerationMagnitude":5.6503253e-05}]