[{"handCompactness":0.28741938,"extensionRatio":0.89684844,"velocityMagnitude":0,"accelerationMagnitude":0},{"handCompactness":0.28722566,"extensionRatio":0.89255065,"velocityMagnitude":0.014689578,"accelerationMagnitude":0.014689578},{"handCompactness":0.28706604,"extensionRatio":0.8944254,"velocityMagnitude":0.01416818,"accelerationMagnitude":-0.00052139815},{"handCompactness":0.28581363,"extensionRatio":0.89241934,"velocityMagnitude":0.013951057,"accelerationMagnitude":-0.00021712296},{"handCompactness":0.28522354,"extensionRatio":0.8845691,"velocityMagnitude":0.012328798,"accelerationMagnitude":-0.0016222587},{"handCompactness":0.28593674,"extensionRatio":0.88081634,"velocityMagnitude":0.013715178,"accelerationMagnitude":0.0013863798},{"handCompactness":0.28572077,"extensionRatio":0.880329,"velocityMagnitude":0.0114471065,"accelerationMagnitude":-0.0022680713},{"handCompactness":0.28450897,"extensionRatio":0.8796848,"velocityMagnitude":0.0132350875,"accelerationMagnitude":0.001787981},{"handCompactness":0.28444678,"extensionRatio":0.87831277,"velocityMagnitude":0.011591749,"accelerationMagnitude":-0.0016433382},{"handCompactness":0.28391612,"extensionRatio":0.8778699,"velocityMagnitude":0.010516604,"accelerationMagnitude":-0.0010751449},{"handCompactness":0.2833231,"extensionRatio":0.8793545,"velocityMagnitude":0.010547528,"accelerationMagnitude":3.0923635e-05},{"handCompactness":0.28109425,"extensionRatio":0.8698846,"velocityMagnitude":0.00973224,"accelerationMagnitude":-0.00081528816},{"handCompactness":0.28087154,"extensionRatio":0.867183,"velocityMagnitude":0.010986932,"accelerationMagnitude":0.0012546917},{"handCompactness":0.28073776,"extensionRatio":0.8607385,"velocityMagnitude":0.014854074,"accelerationMagnitude":0.0038671428},{"handCompactness":0.28047013,"extensionRatio":0.858006,"velocityMagnitude":0.015458448,"accelerationMagnitude":0.0006043734},{"handCompactness":0.2806975,"extensionRatio":0.85828084,"velocityMagnitude":0.016117781,"accelerationMagnitude":0.00065933354},{"handCompactness":0.28057522,"extensionRatio":0.85755163,"velocityMagnitude":0.01600957,"accelerationMagnitude":-0.00010821223},{"handCompactness":0.28072363,"extensionRatio":0.8561351,"velocityMagnitude":0.014560673,"accelerationMagnitude":-0.0014488958},{"handCompactness":0.28040558,"extensionRatio":0.854249,"velocityMagnitude":0.015024026,"accelerationMagnitude":0.00046335254},{"handCompactness":0.28017268,"extensionRatio":0.8516007,"velocityMagnitude":0.019499086,"accelerationMagnitude":0.00447506},{"handCompactness":0.28108343,"extensionRatio":0.85369194,"velocityMagnitude":0.02128723,"accelerationMagnitude":0.0017881449},{"handCompactness":0.28189808,"extensionRatio":0.8620847,"velocityMagnitude":0.02107934,"accelerationMagnitude":-0.00020789169},{"handCompactness":0.28221917,"extensionRatio":0.868214,"velocityMagnitude":0.024442734,"accelerationMagnitude":0.003363395},{"handCompactness":0.28433207,"extensionRatio":0.86843187,"velocityMagnitude":0.024086317,"accelerationMagnitude":-0.00035641715},{"handCompactness":0.28467423,"extensionRatio":0.8746858,"velocityMagnitude":0.019030478,"accelerationMagnitude":-0.005055839},{"handCompactness":0.28352672,"extensionRatio":0.8674671,"velocityMagnitude":0.018216819,"accelerationMagnitude":-0.0008136593},{"handCompactness":0.28485423,"extensionRatio":0.87714416,"velocityMagnitude":0.0108752195,"accelerationMagnitude":-0.007341599},{"handCompactness":0.28444183,"extensionRatio":0.88828117,"velocityMagnitude":0.0076601557,"accelerationMagnitude":-0.0032150638},{"handCompactness":0.28350273,"extensionRatio":0.8866864,"velocityMagnitude":0.010987476,"accelerationMagnitude":0.0033273208},{"handCompactness":0.28177586,"extensionRatio":0.8923038,"velocityMagnitude":0.02818603,"accelerationMagnitude":0.017198555}]