[{"accelerationMagnitude":0,"handCompactness":0.19045556,"extensionRatio":5.601664,"velocityMagnitude":0},{"accelerationMagnitude":0.0013577351,"handCompactness":0.1909755,"extensionRatio":5.529609,"velocityMagnitude":0.0013577351},{"accelerationMagnitude":3.1362986e-05,"handCompactness":0.19018987,"extensionRatio":5.634728,"velocityMagnitude":0.0013890981},{"accelerationMagnitude":0.00079266704,"handCompactness":0.19102661,"extensionRatio":5.506421,"velocityMagnitude":0.0021817652},{"accelerationMagnitude":-0.0008579779,"handCompactness":0.19062147,"extensionRatio":5.470846,"velocityMagnitude":0.0013237873},{"accelerationMagnitude":0.002312604,"handCompactness":0.1904788,"extensionRatio":5.476361,"velocityMagnitude":0.0036363914},{"accelerationMagnitude":-0.0003758981,"handCompactness":0.19040245,"extensionRatio":5.284557,"velocityMagnitude":0.0032604933},{"accelerationMagnitude":0.001277131,"handCompactness":0.18986197,"extensionRatio":5.206551,"velocityMagnitude":0.0045376243},{"accelerationMagnitude":0.00074675167,"handCompactness":0.19077702,"extensionRatio":4.844361,"velocityMagnitude":0.005284376},{"accelerationMagnitude":0.006869081,"handCompactness":0.1894193,"extensionRatio":4.4059978,"velocityMagnitude":0.012153457},{"accelerationMagnitude":0.0033011455,"handCompactness":0.18764658,"extensionRatio":4.364503,"velocityMagnitude":0.015454602},{"accelerationMagnitude":-0.0076774852,"handCompactness":0.1859748,"extensionRatio":4.4655643,"velocityMagnitude":0.007777117},{"accelerationMagnitude":0.007711308,"handCompactness":0.18088074,"extensionRatio":4.689577,"velocityMagnitude":0.015488425},{"accelerationMagnitude":-0.005769804,"handCompactness":0.18132809,"extensionRatio":4.05946,"velocityMagnitude":0.009718621},{"accelerationMagnitude":-0.0034550605,"handCompactness":0.17593524,"extensionRatio":5.211969,"velocityMagnitude":0.0062635606},{"accelerationMagnitude":0.0022705123,"handCompactness":0.17901881,"extensionRatio":4.1382513,"velocityMagnitude":0.008534073},{"accelerationMagnitude":0.001510255,"handCompactness":0.1752491,"extensionRatio":5.105165,"velocityMagnitude":0.010044328},{"accelerationMagnitude":-0.00020122342,"handCompactness":0.17201419,"extensionRatio":5.2422547,"velocityMagnitude":0.0098431045},{"accelerationMagnitude":0.0359618,"handCompactness":0.16426274,"extensionRatio":3.6954658,"velocityMagnitude":0.045804903},{"accelerationMagnitude":-0.03214973,"handCompactness":0.16414058,"extensionRatio":1.9596015,"velocityMagnitude":0.013655174},{"accelerationMagnitude":-0.0041921195,"handCompactness":0.1590673,"extensionRatio":1.8136808,"velocityMagnitude":0.009463054},{"accelerationMagnitude":-0.007506829,"handCompactness":0.16165392,"extensionRatio":1.8839622,"velocityMagnitude":0.001956225},{"accelerationMagnitude":0.0049659107,"handCompactness":0.16508046,"extensionRatio":1.719452,"velocityMagnitude":0.0069221356},{"accelerationMagnitude":-0.0045700837,"handCompactness":0.16684496,"extensionRatio":1.6991767,"velocityMagnitude":0.0023520517},{"accelerationMagnitude":0.002208159,"handCompactness":0.16656975,"extensionRatio":1.7101825,"velocityMagnitude":0.0045602107},{"accelerationMagnitude":0.0007675458,"handCompactness":0.1684181,"extensionRatio":1.6767707,"velocityMagnitude":0.0053277565},{"accelerationMagnitude":-0.0018089872,"handCompactness":0.16753817,"extensionRatio":1.831256,"velocityMagnitude":0.0035187693},{"accelerationMagnitude":0.003760835,"handCompactness":0.1663386,"extensionRatio":2.1109638,"velocityMagnitude":0.007279604},{"accelerationMagnitude":-0.005410049,"handCompactness":0.16555786,"extensionRatio":2.2971957,"velocityMagnitude":0.0018695553},{"accelerationMagnitude":-0.0005741938,"handCompactness":0.16456905,"extensionRatio":2.3128142,"velocityMagnitude":0.0012953616}]