[{"relativeYAcceleration":0,"relativeYVelocity":0,"palmStabilityScore":0},{"relativeYAcceleration":0.0024588108,"relativeYVelocity":0.0024588108,"palmStabilityScore":0.013195336},{"relativeYAcceleration":-0.0022054315,"relativeYVelocity":0.00025337934,"palmStabilityScore":0.009161651},{"relativeYAcceleration":-0.0009062886,"relativeYVelocity":-0.0006529093,"palmStabilityScore":0.0025402308},{"relativeYAcceleration":0.00032278895,"relativeYVelocity":-0.00033012033,"palmStabilityScore":0.0036974847},{"relativeYAcceleration":0.0011590421,"relativeYVelocity":0.0008289218,"palmStabilityScore":0.0025212169},{"relativeYAcceleration":0.0004645884,"relativeYVelocity":0.0012935102,"palmStabilityScore":0.0026633441},{"relativeYAcceleration":-0.0016816258,"relativeYVelocity":-0.00038811564,"palmStabilityScore":0.004623741},{"relativeYAcceleration":0.0031965673,"relativeYVelocity":0.0028084517,"palmStabilityScore":0.0021048188},{"relativeYAcceleration":-0.0027119815,"relativeYVelocity":9.647012e-05,"palmStabilityScore":0.0045295656},{"relativeYAcceleration":-0.00042951107,"relativeYVelocity":-0.00033304095,"palmStabilityScore":0.0035117567},{"relativeYAcceleration":-4.8607588e-05,"relativeYVelocity":-0.00038164854,"palmStabilityScore":0.0037354827},{"relativeYAcceleration":-0.0024059415,"relativeYVelocity":-0.00278759,"palmStabilityScore":0.006555915},{"relativeYAcceleration":0.0026911795,"relativeYVelocity":-9.641051e-05,"palmStabilityScore":0.0038557947},{"relativeYAcceleration":-0.0022467375,"relativeYVelocity":-0.002343148,"palmStabilityScore":0.0020590723},{"relativeYAcceleration":0.0016573071,"relativeYVelocity":-0.00068584085,"palmStabilityScore":0.0012798011},{"relativeYAcceleration":-0.0032722652,"relativeYVelocity":-0.003958106,"palmStabilityScore":0.0015013814},{"relativeYAcceleration":0.0011752844,"relativeYVelocity":-0.0027828217,"palmStabilityScore":0.006838262},{"relativeYAcceleration":0.0005618632,"relativeYVelocity":-0.0022209585,"palmStabilityScore":0.0032863915},{"relativeYAcceleration":-0.0028546154,"relativeYVelocity":-0.005075574,"palmStabilityScore":0.0015525222},{"relativeYAcceleration":-0.008104533,"relativeYVelocity":-0.013180107,"palmStabilityScore":0.0027506053},{"relativeYAcceleration":0.004116744,"relativeYVelocity":-0.009063363,"palmStabilityScore":0.005786538},{"relativeYAcceleration":0.003919035,"relativeYVelocity":-0.005144328,"palmStabilityScore":0.002039045},{"relativeYAcceleration":-0.0056177974,"relativeYVelocity":-0.010762125,"palmStabilityScore":0.006172091},{"relativeYVelocity":-0.008222967,"relativeYAcceleration":0.0025391579,"palmStabilityScore":0.003850609}]