[{"relativeYVelocity":0,"relativeYAcceleration":0,"palmStabilityScore":0},{"relativeYVelocity":4.0084124e-05,"relativeYAcceleration":4.0084124e-05,"palmStabilityScore":0.0015101135},{"relativeYVelocity":-0.0008177757,"relativeYAcceleration":-0.00085785985,"palmStabilityScore":0.0011969805},{"relativeYVelocity":0.00028407574,"relativeYAcceleration":0.0011018515,"palmStabilityScore":0.0015415549},{"relativeYVelocity":9.715557e-05,"relativeYAcceleration":-0.00018692017,"palmStabilityScore":0.00021350384},{"relativeYVelocity":0.00030434132,"relativeYAcceleration":0.00020718575,"palmStabilityScore":0.0005865097},{"relativeYVelocity":6.905198e-05,"relativeYAcceleration":-0.00023528934,"palmStabilityScore":0.00095406175},{"relativeYVelocity":-0.0004325509,"relativeYAcceleration":-0.0005016029,"palmStabilityScore":0.0014027357},{"relativeYVelocity":0.00032117963,"relativeYAcceleration":0.00075373054,"palmStabilityScore":0.0014376938},{"relativeYVelocity":-0.0003966987,"relativeYAcceleration":-0.00071787834,"palmStabilityScore":0.00067713857},{"relativeYVelocity":0.0014374852,"relativeYAcceleration":0.0018341839,"palmStabilityScore":0.0013776422},{"relativeYVelocity":-0.00066170096,"relativeYAcceleration":-0.0020991862,"palmStabilityScore":0.0005761087},{"relativeYVelocity":-0.000446707,"relativeYAcceleration":0.00021499395,"palmStabilityScore":0.00059762597},{"relativeYVelocity":-0.00045832992,"relativeYAcceleration":-1.1622906e-05,"palmStabilityScore":0.0010997951},{"relativeYVelocity":0.0002476573,"relativeYAcceleration":0.0007059872,"palmStabilityScore":0.0013771653},{"relativeYVelocity":0.0007072091,"relativeYAcceleration":0.0004595518,"palmStabilityScore":0.0020529628},{"relativeYVelocity":-0.00013577938,"relativeYAcceleration":-0.0008429885,"palmStabilityScore":0.0009613633},{"relativeYVelocity":-0.00014781952,"relativeYAcceleration":-1.2040138e-05,"palmStabilityScore":0.001060605},{"relativeYVelocity":-0.00022560358,"relativeYAcceleration":-7.778406e-05,"palmStabilityScore":0.0006029606},{"relativeYVelocity":0.0004645884,"relativeYAcceleration":0.000690192,"palmStabilityScore":0.00018444657},{"relativeYVelocity":5.340576e-05,"relativeYAcceleration":-0.00041118264,"palmStabilityScore":0.0019100308},{"relativeYVelocity":-0.0012283623,"relativeYAcceleration":-0.0012817681,"palmStabilityScore":0.0022490919},{"relativeYVelocity":0.0010222495,"relativeYAcceleration":0.0022506118,"palmStabilityScore":0.00059494376},{"relativeYVelocity":-0.00031259656,"relativeYAcceleration":-0.001334846,"palmStabilityScore":0.00041756034},{"relativeYVelocity":7.164478e-05,"relativeYAcceleration":0.00038424134,"palmStabilityScore":0.00042009354}]