[{"palmStabilityScore":0,"relativeYAcceleration":0,"relativeYVelocity":0},{"palmStabilityScore":0.0036943257,"relativeYAcceleration":0.0007236004,"relativeYVelocity":0.0007236004},{"palmStabilityScore":0.007723272,"relativeYAcceleration":-0.0043325126,"relativeYVelocity":-0.0036089122},{"palmStabilityScore":0.0027804375,"relativeYAcceleration":-1.9162893e-05,"relativeYVelocity":-0.0036280751},{"palmStabilityScore":0.0064037144,"relativeYAcceleration":0.0073085427,"relativeYVelocity":0.0036804676},{"palmStabilityScore":0.016517907,"relativeYAcceleration":-0.0068175197,"relativeYVelocity":-0.003137052},{"palmStabilityScore":0.035826087,"relativeYAcceleration":-0.004564464,"relativeYVelocity":-0.007701516},{"palmStabilityScore":0.042436153,"relativeYAcceleration":-0.0022458434,"relativeYVelocity":-0.00994736},{"palmStabilityScore":0.08593303,"relativeYAcceleration":0.009855956,"relativeYVelocity":-9.140372e-05},{"palmStabilityScore":0.027522355,"relativeYAcceleration":-0.016462624,"relativeYVelocity":-0.016554028},{"palmStabilityScore":0.006676972,"relativeYAcceleration":0.006187588,"relativeYVelocity":-0.01036644},{"relativeYVelocity":0.004523039,"palmStabilityScore":0.028295398,"relativeYAcceleration":0.014889479},{"relativeYVelocity":-0.011244863,"palmStabilityScore":0.010678798,"relativeYAcceleration":-0.015767902},{"relativeYVelocity":-0.008996397,"palmStabilityScore":0.0034376085,"relativeYAcceleration":0.002248466},{"relativeYVelocity":-0.010031909,"palmStabilityScore":0.013232738,"relativeYAcceleration":-0.0010355115},{"relativeYVelocity":-0.009697914,"palmStabilityScore":0.0098297,"relativeYAcceleration":0.00033399463},{"relativeYVelocity":-0.008957356,"palmStabilityScore":0.005701989,"relativeYAcceleration":0.0007405579},{"relativeYVelocity":-0.0064831674,"palmStabilityScore":0.005610734,"relativeYAcceleration":0.0024741888},{"relativeYVelocity":-0.003268063,"palmStabilityScore":0.004653573,"relativeYAcceleration":0.0032151043},{"relativeYVelocity":0.0039350092,"palmStabilityScore":0.0014804304,"relativeYAcceleration":0.0072030723},{"relativeYVelocity":0.00012382865,"palmStabilityScore":0.0027115345,"relativeYAcceleration":-0.0038111806},{"relativeYVelocity":0.00038778782,"palmStabilityScore":0.0029984415,"relativeYAcceleration":0.00026395917},{"relativeYVelocity":0.0003733933,"palmStabilityScore":0.0017088056,"relativeYAcceleration":-1.4394522e-05},{"relativeYVelocity":-0.00015568733,"palmStabilityScore":0.00024101138,"relativeYAcceleration":-0.00052908063},{"relativeYVelocity":-0.00013187528,"palmStabilityScore":0.0006522238,"relativeYAcceleration":2.3812056e-05}]