[{"relativeYAcceleration":0,"palmStabilityScore":0,"relativeYVelocity":0},{"relativeYAcceleration":0.00074899197,"palmStabilityScore":0.0016677082,"relativeYVelocity":0.00074899197},{"relativeYAcceleration":-0.0006800592,"palmStabilityScore":0.00063180923,"relativeYVelocity":6.893277e-05},{"relativeYAcceleration":-0.00075513124,"palmStabilityScore":0.0023900568,"relativeYVelocity":-0.0006861985},{"relativeYAcceleration":0.0017835498,"palmStabilityScore":0.002973348,"relativeYVelocity":0.0010973513},{"relativeYAcceleration":-0.0027201474,"palmStabilityScore":0.0035721064,"relativeYVelocity":-0.0016227961},{"relativeYAcceleration":0.0023608804,"palmStabilityScore":0.0014828742,"relativeYVelocity":0.0007380843},{"relativeYAcceleration":-0.0011895895,"palmStabilityScore":0.0013419092,"relativeYVelocity":-0.00045150518},{"relativeYAcceleration":0.0019210279,"palmStabilityScore":0.0020868182,"relativeYVelocity":0.0014695227},{"relativeYAcceleration":-0.0026227832,"palmStabilityScore":0.0014718175,"relativeYVelocity":-0.0011532605},{"relativeYAcceleration":0.0020407736,"palmStabilityScore":0.0017047524,"relativeYVelocity":0.00088751316},{"relativeYAcceleration":-0.0021129549,"palmStabilityScore":0.0018513203,"relativeYVelocity":-0.0012254417},{"relativeYAcceleration":0.0022368133,"palmStabilityScore":0.0028824508,"relativeYVelocity":0.0010113716},{"relativeYAcceleration":-0.0016893148,"palmStabilityScore":0.0019096732,"relativeYVelocity":-0.00067794323},{"relativeYAcceleration":0.0015141666,"palmStabilityScore":0.0025616586,"relativeYVelocity":0.00083622336},{"relativeYAcceleration":-0.0017353594,"palmStabilityScore":0.001681596,"relativeYVelocity":-0.00089913607},{"relativeYAcceleration":0.0023021102,"palmStabilityScore":0.0016597211,"relativeYVelocity":0.0014029741},{"relativeYAcceleration":-0.002794981,"palmStabilityScore":0.0014203191,"relativeYVelocity":-0.0013920069},{"relativeYAcceleration":0.0026299357,"palmStabilityScore":0.0013887286,"relativeYVelocity":0.0012379289},{"relativeYAcceleration":-0.0025369227,"palmStabilityScore":0.0011180341,"relativeYVelocity":-0.0012989938},{"relativeYAcceleration":0.0023449361,"palmStabilityScore":0.0023134649,"relativeYVelocity":0.0010459423},{"relativeYAcceleration":-0.0018455982,"palmStabilityScore":0.0009666383,"relativeYVelocity":-0.0007996559},{"relativeYAcceleration":0.001391381,"palmStabilityScore":0.0035260916,"relativeYVelocity":0.0005917251},{"relativeYAcceleration":-0.0010089278,"palmStabilityScore":0.0010250807,"relativeYVelocity":-0.0004172027},{"relativeYAcceleration":0.0015815794,"palmStabilityScore":0.0021498203,"relativeYVelocity":0.0011643767}]