[{"relativeYVelocity":0,"palmStabilityScore":0,"relativeYAcceleration":0},{"relativeYVelocity":-0.0009304285,"palmStabilityScore":0.00090920925,"relativeYAcceleration":-0.0009304285},{"relativeYVelocity":0.00040075183,"palmStabilityScore":0.00076940656,"relativeYAcceleration":0.0013311803},{"relativeYVelocity":-0.00048211217,"palmStabilityScore":0.0013853014,"relativeYAcceleration":-0.000882864},{"relativeYVelocity":0.00015479326,"palmStabilityScore":0.00040072203,"relativeYAcceleration":0.00063690543},{"relativeYVelocity":-0.00025931,"palmStabilityScore":0.0026575625,"relativeYAcceleration":-0.00041410327},{"relativeYVelocity":0.0005733967,"palmStabilityScore":0.0023128986,"relativeYAcceleration":0.0008327067},{"relativeYVelocity":-0.00037404895,"palmStabilityScore":0.0013938844,"relativeYAcceleration":-0.00094744563},{"relativeYVelocity":0.00035104156,"palmStabilityScore":0.0007264912,"relativeYAcceleration":0.0007250905},{"relativeYVelocity":-0.0004014969,"palmStabilityScore":0.0002863407,"relativeYAcceleration":-0.00075253844},{"relativeYVelocity":-0.00015893579,"palmStabilityScore":0.0012129843,"relativeYAcceleration":0.0002425611},{"relativeYVelocity":0.0010721684,"palmStabilityScore":0.0016278028,"relativeYAcceleration":0.0012311041},{"relativeYVelocity":-0.0013085902,"palmStabilityScore":0.0018357337,"relativeYAcceleration":-0.0023807585},{"relativeYVelocity":0.00062149763,"palmStabilityScore":0.000495553,"relativeYAcceleration":0.0019300878},{"relativeYVelocity":0.0005707443,"palmStabilityScore":0.00084611773,"relativeYAcceleration":-5.0753355e-05},{"relativeYVelocity":-0.00038567185,"palmStabilityScore":0.000988692,"relativeYAcceleration":-0.00095641613},{"relativeYVelocity":-0.00027608871,"palmStabilityScore":0.00143224,"relativeYAcceleration":0.00010958314},{"relativeYVelocity":4.8220158e-05,"palmStabilityScore":0.0014612079,"relativeYAcceleration":0.00032430887},{"relativeYVelocity":0.00042766333,"palmStabilityScore":0.0025479794,"relativeYAcceleration":0.00037944317},{"relativeYVelocity":-0.0005195737,"palmStabilityScore":0.0012896657,"relativeYAcceleration":-0.000947237},{"relativeYVelocity":4.929304e-05,"palmStabilityScore":0.00059592724,"relativeYAcceleration":0.00056886673},{"relativeYVelocity":0.00022351742,"palmStabilityScore":0.0014791489,"relativeYAcceleration":0.00017422438},{"relativeYVelocity":0.00015762448,"palmStabilityScore":0.0006825626,"relativeYAcceleration":-6.5892935e-05},{"relativeYVelocity":-0.00015255809,"palmStabilityScore":0.0016838014,"relativeYAcceleration":-0.00031018257},{"relativeYVelocity":0.00052684546,"palmStabilityScore":0.0012353659,"relativeYAcceleration":0.00067940354}]