[{"relativeYVelocity":0,"relativeYAcceleration":0,"palmStabilityScore":0},{"relativeYVelocity":0.00021773577,"relativeYAcceleration":0.00021773577,"palmStabilityScore":0.0033067167},{"relativeYVelocity":-0.000106334686,"relativeYAcceleration":-0.00032407045,"palmStabilityScore":0.0005929172},{"relativeYVelocity":8.8602304e-05,"relativeYAcceleration":0.00019493699,"palmStabilityScore":0.0020689964},{"relativeYVelocity":-5.3226948e-05,"relativeYAcceleration":-0.00014182925,"palmStabilityScore":0.001716584},{"relativeYVelocity":-0.0004555881,"relativeYAcceleration":-0.00040236115,"palmStabilityScore":0.0006579459},{"relativeYVelocity":0.0001295805,"relativeYAcceleration":0.0005851686,"palmStabilityScore":0.0006816685},{"relativeYVelocity":0.00065898895,"relativeYAcceleration":0.00052940845,"palmStabilityScore":0.00087329745},{"relativeYVelocity":-0.00088730454,"relativeYAcceleration":-0.0015462935,"palmStabilityScore":0.0009561479},{"relativeYVelocity":0.0002642572,"relativeYAcceleration":0.0011515617,"palmStabilityScore":0.0009595454},{"relativeYVelocity":0.0005736649,"relativeYAcceleration":0.0003094077,"palmStabilityScore":0.0007131994},{"relativeYVelocity":-0.0004937351,"relativeYAcceleration":-0.0010674,"palmStabilityScore":0.00114277},{"relativeYVelocity":6.505847e-05,"relativeYAcceleration":0.00055879354,"palmStabilityScore":0.00067171454},{"relativeYVelocity":-6.848574e-05,"relativeYAcceleration":-0.0001335442,"palmStabilityScore":0.0009507239},{"relativeYVelocity":0.0003349185,"relativeYAcceleration":0.00040340424,"palmStabilityScore":0.000382334},{"relativeYVelocity":1.5288591e-05,"relativeYAcceleration":-0.0003196299,"palmStabilityScore":0.0010308325},{"relativeYVelocity":0.0001411438,"relativeYAcceleration":0.00012585521,"palmStabilityScore":0.00060749054},{"relativeYVelocity":-0.00042751431,"relativeYAcceleration":-0.0005686581,"palmStabilityScore":0.0006457269},{"relativeYVelocity":-0.00034451485,"relativeYAcceleration":8.299947e-05,"palmStabilityScore":0.0011017919},{"relativeYVelocity":0.0005043447,"relativeYAcceleration":0.00084885955,"palmStabilityScore":0.0010580719},{"relativeYVelocity":-0.0008814335,"relativeYAcceleration":-0.0013857782,"palmStabilityScore":0.0010913312},{"relativeYVelocity":0.00037562847,"relativeYAcceleration":0.001257062,"palmStabilityScore":0.00068482757},{"relativeYVelocity":0.00079372525,"relativeYAcceleration":0.00041809678,"palmStabilityScore":0.00070858},{"relativeYVelocity":-9.7841024e-05,"relativeYAcceleration":-0.0008915663,"palmStabilityScore":0.00057813525},{"relativeYVelocity":0.00039613247,"relativeYAcceleration":0.0004939735,"palmStabilityScore":0.0012895167}]