[{"relativeYAcceleration":0,"relativeYVelocity":0},{"relativeYVelocity":0.00020697713,"relativeYAcceleration":0.00020697713},{"relativeYVelocity":-0.0005712211,"relativeYAcceleration":-0.00077819824},{"relativeYVelocity":0.00081792474,"relativeYAcceleration":0.0013891459},{"relativeYVelocity":-0.00067588687,"relativeYAcceleration":-0.0014938116},{"relativeYVelocity":0.000746727,"relativeYAcceleration":0.0014226139},{"relativeYVelocity":9.462237e-05,"relativeYAcceleration":-0.0006521046},{"relativeYVelocity":0.0007368028,"relativeYAcceleration":0.00064218044},{"relativeYVelocity":-0.0011693537,"relativeYAcceleration":-0.0019061565},{"relativeYVelocity":-0.00025454164,"relativeYAcceleration":0.0009148121},{"relativeYVelocity":0.0006660521,"relativeYAcceleration":0.00092059374},{"relativeYVelocity":-0.00019228458,"relativeYAcceleration":-0.0008583367},{"relativeYVelocity":-0.00012740493,"relativeYAcceleration":6.4879656e-05},{"relativeYVelocity":-0.0003978312,"relativeYAcceleration":-0.00027042627},{"relativeYVelocity":7.95722e-06,"relativeYAcceleration":0.00040578842},{"relativeYAcceleration":0.00017094612,"relativeYVelocity":0.00017890334},{"relativeYAcceleration":-4.4196844e-05,"relativeYVelocity":0.0001347065},{"relativeYAcceleration":-2.4408102e-05,"relativeYVelocity":0.000110298395},{"relativeYAcceleration":-0.0003632009,"relativeYVelocity":-0.0002529025},{"relativeYAcceleration":0.00037753582,"relativeYVelocity":0.00012463331},{"relativeYAcceleration":-0.00018253922,"relativeYVelocity":-5.7905912e-05},{"relativeYAcceleration":0.00023809075,"relativeYVelocity":0.00018018484},{"relativeYAcceleration":-0.0004579723,"relativeYVelocity":-0.00027778745},{"relativeYAcceleration":0.00038278103,"relativeYVelocity":0.00010499358},{"relativeYAcceleration":0.00012752414,"relativeYVelocity":0.00023251772}]