[{"relativeYAcceleration":0,"relativeYVelocity":0},{"relativeYVelocity":-0.0010254085,"relativeYAcceleration":-0.0010254085},{"relativeYVelocity":0.00045385957,"relativeYAcceleration":0.0014792681},{"relativeYVelocity":-0.0017358959,"relativeYAcceleration":-0.0021897554},{"relativeYVelocity":0.0018236637,"relativeYAcceleration":0.0035595596},{"relativeYVelocity":6.625056e-05,"relativeYAcceleration":-0.0017574131},{"relativeYVelocity":-0.00094136596,"relativeYAcceleration":-0.0010076165},{"relativeYVelocity":0.00046780705,"relativeYAcceleration":0.001409173},{"relativeYVelocity":-5.8829784e-05,"relativeYAcceleration":-0.00052663684},{"relativeYVelocity":0.00011855364,"relativeYAcceleration":0.00017738342},{"relativeYVelocity":0.0002399385,"relativeYAcceleration":0.00012138486},{"relativeYVelocity":0.0002990961,"relativeYAcceleration":5.915761e-05},{"relativeYVelocity":-0.00040233135,"relativeYAcceleration":-0.00070142746},{"relativeYVelocity":0.00037556887,"relativeYAcceleration":0.0007779002},{"relativeYVelocity":-0.0005803406,"relativeYAcceleration":-0.0009559095},{"relativeYAcceleration":0.0010239482,"relativeYVelocity":0.00044360757},{"relativeYAcceleration":-0.0011434257,"relativeYVelocity":-0.00069981813},{"relativeYAcceleration":0.00058054924,"relativeYVelocity":-0.000119268894},{"relativeYAcceleration":0.0004504919,"relativeYVelocity":0.000331223},{"relativeYAcceleration":-0.0006656647,"relativeYVelocity":-0.00033444166},{"relativeYAcceleration":0.0008879006,"relativeYVelocity":0.0005534589},{"relativeYAcceleration":-0.0009872019,"relativeYVelocity":-0.000433743},{"relativeYAcceleration":0.0010283887,"relativeYVelocity":0.00059464574},{"relativeYAcceleration":-0.00094017386,"relativeYVelocity":-0.00034552813},{"relativeYAcceleration":-0.00023066998,"relativeYVelocity":-0.0005761981}]