[{"relativeYAcceleration":0,"relativeYVelocity":0},{"relativeYVelocity":0.00064468384,"relativeYAcceleration":0.00064468384},{"relativeYVelocity":6.830692e-05,"relativeYAcceleration":-0.0005763769},{"relativeYVelocity":-0.00042754412,"relativeYAcceleration":-0.00049585104},{"relativeYVelocity":-0.00033146143,"relativeYAcceleration":9.608269e-05},{"relativeYVelocity":0.00039690733,"relativeYAcceleration":0.00072836876},{"relativeYVelocity":0.0005902052,"relativeYAcceleration":0.00019329786},{"relativeYVelocity":0.00046527386,"relativeYAcceleration":-0.00012493134},{"relativeYVelocity":-0.0007587373,"relativeYAcceleration":-0.0012240112},{"relativeYVelocity":-0.00065535307,"relativeYAcceleration":0.00010338426},{"relativeYVelocity":-0.00032368302,"relativeYAcceleration":0.00033167005},{"relativeYVelocity":0.0006676018,"relativeYAcceleration":0.0009912848},{"relativeYVelocity":0.001057893,"relativeYAcceleration":0.0003902912},{"relativeYVelocity":-0.00020480156,"relativeYAcceleration":-0.0012626946},{"relativeYVelocity":-0.00023534894,"relativeYAcceleration":-3.054738e-05},{"relativeYAcceleration":0.00046777725,"relativeYVelocity":0.00023242831},{"relativeYAcceleration":-4.5001507e-06,"relativeYVelocity":0.00022792816},{"relativeYAcceleration":-0.00026792288,"relativeYVelocity":-3.9994717e-05},{"relativeYAcceleration":0.00024360418,"relativeYVelocity":0.00020360947},{"relativeYAcceleration":-0.00020262599,"relativeYVelocity":9.834766e-07},{"relativeYAcceleration":-0.00057438016,"relativeYVelocity":-0.0005733967},{"relativeYAcceleration":0.0003553033,"relativeYVelocity":-0.0002180934},{"relativeYAcceleration":0.00032761693,"relativeYVelocity":0.000109523535},{"relativeYAcceleration":-8.0645084e-05,"relativeYVelocity":2.887845e-05},{"relativeYAcceleration":-4.3451786e-05,"relativeYVelocity":-1.4573336e-05}]