[{"relativeZAcceleration":0,"relativeZVelocity":0},{"relativeZAcceleration":-0.0003144606,"relativeZVelocity":-0.0003144606},{"relativeZAcceleration":0.002094645,"relativeZVelocity":0.0017801845},{"relativeZAcceleration":-0.0027915048,"relativeZVelocity":-0.0010113204},{"relativeZAcceleration":0.0016140761,"relativeZVelocity":0.0006027557},{"relativeZAcceleration":-0.000992748,"relativeZVelocity":-0.00038999226},{"relativeZAcceleration":-0.0005972786,"relativeZVelocity":-0.0009872708},{"relativeZAcceleration":0.0013966234,"relativeZVelocity":0.0004093526},{"relativeZAcceleration":1.962576e-05,"relativeZVelocity":0.00042897835},{"relativeZAcceleration":-0.0008394662,"relativeZVelocity":-0.00041048788},{"relativeZAcceleration":-0.00042641535,"relativeZVelocity":-0.00083690323},{"relativeZAcceleration":-0.0010121958,"relativeZVelocity":-0.0018490991},{"relativeZAcceleration":0.0008675335,"relativeZVelocity":-0.0009815656},{"relativeZAcceleration":0.000110791996,"relativeZVelocity":-0.00087077357},{"relativeZAcceleration":0.00079260394,"relativeZVelocity":-7.816963e-05}]